phi/__init__.py
phi/build_dataset.py
phi/core/__init__.py
phi/core/attend.py
phi/core/autoregressive_wrapper.py
phi/core/flash.py
phi/core/transformer.py
phi/finetuning/README.md
phi/inference.py
phi/model.py
phi/old/sophia.py
phi/old/training.py
phi/old/training_sophia.py
phi/train.py
phi/utils/decoupled_optimizer.py
phi/utils/helpers.py
phi/utils/rf_utils.py
phi/utils/stable_adamw.py
phi_torch-0.0.4.dist-info/LICENSE
phi_torch-0.0.4.dist-info/WHEEL
phi_torch-0.0.4.dist-info/METADATA
phi_torch-0.0.4.dist-info/RECORD
